Httppool/__init__.py
Httppool/deamon.py
httppool-1.0.23.dist-info/METADATA
httppool-1.0.23.dist-info/WHEEL
httppool-1.0.23.dist-info/top_level.txt
httppool-1.0.23.dist-info/RECORD
