Metadata-Version: 2.4
Name: Httppool
Version: 1.0.23
Summary: Get and storing the HTML data of a website using a cache system.
Home-page: https://github.com/alexdevzz/httppool-ce-services.git
Author: alexdev
Author-email: alexdev.workenv@gmail.com
Project-URL: Bug Tracker, https://github.com/alexdevzz/httppool-ce-services/issues
Classifier: Programming Language :: Python :: 3
Classifier: License :: OSI Approved :: MIT License
Classifier: Operating System :: Unix
Requires-Python: >=3.8
Requires-Dist: requests
Dynamic: author
Dynamic: author-email
Dynamic: classifier
Dynamic: description
Dynamic: description-content-type
Dynamic: home-page
Dynamic: project-url
Dynamic: requires-dist
Dynamic: requires-python
Dynamic: summary
